{"backend_java_mybatis初步入门.md":"4346c2f0","backend_java_servlet初步入门.md":"ac3b0283","backend_java_springboot初步入门.md":"9c24b9a9","backend_java_springmvc初步入门.md":"ee786519","backend_java_spring初步入门.md":"be47aee9","backend_java_index.md":"f84f10ba","backend_index.md":"3c7f5b88","frontend_css_bfc.md":"6a14cb78","frontend_css_index.md":"e5842d50","frontend_frame_vue2_前端初步调试.md":"66b1a0b9","frontend_frame_index.md":"2327b24b","frontend_frame_pack_gulp.md":"4ae48ae6","frontend_frame_pack_rollup.md":"9a8a437d","frontend_html_basic_html基础知识记录.md":"e8f3410e","frontend_html_question_html一些页面问题记录.md":"b4e0fffb","frontend_html_index.md":"47c7c189","frontend_javascript_index.md":"b5897712","frontend_javascript_关于ecmascript.md":"4dda2af6","frontend_typescript_typescript入门.md":"203ca27f","frontend_typescript_index.md":"f00537ff","index.md":"ad3fc0ed","other_index.md":"dc6efb08"}
